README.rst
setup.py
optypecheck.egg-info/PKG-INFO
optypecheck.egg-info/SOURCES.txt
optypecheck.egg-info/dependency_links.txt
optypecheck.egg-info/top_level.txt
optypecheck.egg-info/zip-safe
typecheck/__init__.py
typecheck/types.py