Metadata-Version: 1.1
Name: optypecheck
Version: 17
Summary: A non intrusive and optional *type checking for Python 3* using annotations
Home-page: https://bitbucket.org/carlopires/optypecheck
Author: Carlo Pires
Author-email: carlopires@gmail.com
License: UNKNOWN
Platform: any
Classifier: Development Status :: 5 - Production/Stable
Classifier: Intended Audience :: Developers
Classifier: License :: OSI Approved :: MIT License
Classifier: Operating System :: OS Independent
Classifier: Programming Language :: Python
Classifier: Programming Language :: Python :: 3
Classifier: Programming Language :: Python :: Implementation :: CPython
Classifier: Topic :: Software Development :: Testing
Classifier: Topic :: Software Development :: Libraries
Classifier: Topic :: Software Development :: Libraries :: Python Modules
Classifier: Topic :: Utilities
